kitbag/__init__.py
kitbag/plots/__init__.py
kitbag/plots/altair_plot.py
kitbag/plots/bar_charts.py
kitbag/plots/line_charts.py
kitbag/plots/tables.py
kitbag/utils/__init__.py
kitbag/utils/colors.py
kitbag/utils/utilities.py
kitbag-0.0.8.dist-info/LICENSE
kitbag-0.0.8.dist-info/METADATA
kitbag-0.0.8.dist-info/WHEEL
kitbag-0.0.8.dist-info/top_level.txt
kitbag-0.0.8.dist-info/RECORD
