Metadata-Version: 2.1
Name: kitbag
Version: 0.0.8
Summary: Kitbag with functions, metadata, plots etc. that are used within FCN and RTD
Home-page: UNKNOWN
Author: UNKNOWN
Author-email: UNKNOWN
License: UNKNOWN
Platform: UNKNOWN
